Metadata-Version: 1.0
Name: probab-dsnd
Version: 0.1
Summary: Gaussian and Binomial distributions
Home-page: UNKNOWN
Author: Sabin Adhikari
Author-email: adhikarisabin258@gmail.com
License: UNKNOWN
Platform: UNKNOWN
